dash_pdf_plus/_DashPdf.py
dash_pdf_plus/__init__.py
dash_pdf_plus/_imports_.py
dash_pdf_plus/dash_pdf_plus.min.js
dash_pdf_plus/dash_pdf_plus.min.js.LICENSE.txt
dash_pdf_plus/dash_pdf_plus.min.js.map
dash_pdf_plus/metadata.json
dash_pdf_plus/package-info.json
dash_pdf_plus/pdf.worker.min.mjs
dash_pdf_plus/pdf.worker.min.mjs.LICENSE.txt
dash_pdf_plus-0.0.5.dist-info/licenses/LICENSE
dash_pdf_plus-0.0.5.dist-info/METADATA
dash_pdf_plus-0.0.5.dist-info/WHEEL
dash_pdf_plus-0.0.5.dist-info/top_level.txt
dash_pdf_plus-0.0.5.dist-info/RECORD
