Metadata-Version: 2.4
Name: dash-pdf-plus
Version: 0.0.5
Summary: A Dash component library for rendering PDF documents with enhanced features.
Author: Yasas Senarath
License: Apache-2.0
Classifier: Framework :: Dash
License-File: LICENSE
Requires-Dist: requests
Dynamic: author
Dynamic: classifier
Dynamic: description
Dynamic: description-content-type
Dynamic: license
Dynamic: license-file
Dynamic: requires-dist
Dynamic: summary
